Metadata-Version: 1.0
Name: felzenszwalb-segmentation
Version: 0.1.1
Summary: Implementation of Efficient Graph-Based Image Segmentation
Home-page: UNKNOWN
Author: Soumik Rakshit
Author-email: 19soumik.rakshit96@gmail.com
License: UNKNOWN
Platform: UNKNOWN
